bss_direct_inject/__init__.py
bss_direct_inject/async_client.py
bss_direct_inject/client.py
bss_direct_inject/protocol.py
bss_direct_inject/py.typed
bss_direct_inject-0.1.3.dist-info/WHEEL
bss_direct_inject-0.1.3.dist-info/METADATA
bss_direct_inject-0.1.3.dist-info/RECORD
