Metadata-Version: 2.3
Name: bss-direct-inject
Version: 0.1.3
Summary: Soundweb London Direct Inject protocol helpers for BSS BLU devices.
Author: Zac Oler
Author-email: Zac Oler <zac.oler@gmail.com>
Requires-Python: >=3.14
